32bitCPU-VHDL/src/Control_Unit.vhd
library IEEE;
use IEEE.STD_LOGIC_1164.ALL;

-- File: Control_Unit.vhd
-- Entity: Control_Unit_VHDL
-- Description: Main control decoder for 32-bit single-cycle MIPS.
-- Author: <author>
-- Date: <date>

entity Control_Unit_VHDL is
    port (
        opcode       : in  std_logic_vector(5 downto 0);
        reset        : in  std_logic;
        reg_dst      : out std_logic_vector(1 downto 0);
        mem_to_reg   : out std_logic_vector(1 downto 0);
        alu_op       : out std_logic_vector(1 downto 0);
        jump         : out std_logic;
        branch       : out std_logic;
        mem_read     : out std_logic;
        mem_write    : out std_logic;
        alu_src      : out std_logic;
        reg_write    : out std_logic;
        sign_or_zero : out std_logic
    );
end Control_Unit_VHDL;

architecture Behavioral of Control_Unit_VHDL is
begin
    -- Combinational main control decode.
    process (reset, opcode)
    begin
        if reset = '1' then
            reg_dst      <= "00";
            mem_to_reg   <= "00";
            alu_op       <= "00";
            jump         <= '0';
            branch       <= '0';
            mem_read     <= '0';
            mem_write    <= '0';
            alu_src      <= '0';
            reg_write    <= '0';
            sign_or_zero <= '0';
        else
            case opcode is
                when "000000" =>
                    reg_dst      <= "01";
                    mem_to_reg   <= "00";
                    alu_op       <= "00";
                    jump         <= '0';
                    branch       <= '0';
                    mem_read     <= '0';
                    mem_write    <= '0';
                    alu_src      <= '0';
                    reg_write    <= '1';
                    sign_or_zero <= '0';
                when "100011" =>
                    reg_dst      <= "00";
                    mem_to_reg   <= "01";
                    alu_op       <= "11";
                    jump         <= '0';
                    branch       <= '0';
                    mem_read     <= '1';
                    mem_write    <= '0';
                    alu_src      <= '1';
                    reg_write    <= '1';
                    sign_or_zero <= '1';
                when "101011" =>
                    reg_dst      <= "00";
                    mem_to_reg   <= "00";
                    alu_op       <= "11";
                    jump         <= '0';
                    branch       <= '0';
                    mem_read     <= '0';
                    mem_write    <= '1';
                    alu_src      <= '1';
                    reg_write    <= '0';
                    sign_or_zero <= '1';
                when "000100" =>
                    reg_dst      <= "00";
                    mem_to_reg   <= "00";
                    alu_op       <= "01";
                    jump         <= '0';
                    branch       <= '1';
                    mem_read     <= '0';
                    mem_write    <= '0';
                    alu_src      <= '0';
                    reg_write    <= '0';
                    sign_or_zero <= '1';
                when "001000" =>
                    reg_dst      <= "00";
                    mem_to_reg   <= "00";
                    alu_op       <= "11";
                    jump         <= '0';
                    branch       <= '0';
                    mem_read     <= '0';
                    mem_write    <= '0';
                    alu_src      <= '1';
                    reg_write    <= '1';
                    sign_or_zero <= '1';
                when "001010" =>
                    reg_dst      <= "00";
                    mem_to_reg   <= "00";
                    alu_op       <= "10";
                    jump         <= '0';
                    branch       <= '0';
                    mem_read     <= '0';
                    mem_write    <= '0';
                    alu_src      <= '1';
                    reg_write    <= '1';
                    sign_or_zero <= '1';
                when "000010" =>
                    reg_dst      <= "00";
                    mem_to_reg   <= "00";
                    alu_op       <= "00";
                    jump         <= '1';
                    branch       <= '0';
                    mem_read     <= '0';
                    mem_write    <= '0';
                    alu_src      <= '0';
                    reg_write    <= '0';
                    sign_or_zero <= '0';
                when "000011" =>
                    reg_dst      <= "10";
                    mem_to_reg   <= "10";
                    alu_op       <= "00";
                    jump         <= '1';
                    branch       <= '0';
                    mem_read     <= '0';
                    mem_write    <= '0';
                    alu_src      <= '0';
                    reg_write    <= '1';
                    sign_or_zero <= '0';
                when others =>
                    reg_dst      <= "00";
                    mem_to_reg   <= "00";
                    alu_op       <= "00";
                    jump         <= '0';
                    branch       <= '0';
                    mem_read     <= '0';
                    mem_write    <= '0';
                    alu_src      <= '0';
                    reg_write    <= '0';
                    sign_or_zero <= '0';
            end case;
        end if;
    end process;
end Behavioral;

32bitCPU-VHDL/testbench/TB_Control_Unit.vhd
library IEEE;
use IEEE.STD_LOGIC_1164.ALL;

-- File: TB_Control_Unit.vhd
-- Entity: TB_Control_Unit
-- Description: Self-checking testbench for Control_Unit_VHDL.
-- Author: <author>
-- Date: <date>

entity TB_Control_Unit is
end TB_Control_Unit;

architecture Behavioral of TB_Control_Unit is
    signal opcode       : std_logic_vector(5 downto 0) := (others => '0');
    signal reset        : std_logic := '0';
    signal reg_dst      : std_logic_vector(1 downto 0);
    signal mem_to_reg   : std_logic_vector(1 downto 0);
    signal alu_op       : std_logic_vector(1 downto 0);
    signal jump         : std_logic;
    signal branch       : std_logic;
    signal mem_read     : std_logic;
    signal mem_write    : std_logic;
    signal alu_src      : std_logic;
    signal reg_write    : std_logic;
    signal sign_or_zero : std_logic;
begin
    uut: entity work.Control_Unit_VHDL
        port map (
            opcode       => opcode,
            reset        => reset,
            reg_dst      => reg_dst,
            mem_to_reg   => mem_to_reg,
            alu_op       => alu_op,
            jump         => jump,
            branch       => branch,
            mem_read     => mem_read,
            mem_write    => mem_write,
            alu_src      => alu_src,
            reg_write    => reg_write,
            sign_or_zero => sign_or_zero
        );

    stim_proc: process
    begin
        -- Reset check.
        reset <= '1';
        opcode <= "000000";
        wait for 10 ns;
        assert reg_dst = "00" and mem_to_reg = "00" and alu_op = "00" and
               jump = '0' and branch = '0' and mem_read = '0' and mem_write = '0' and
               alu_src = '0' and reg_write = '0' and sign_or_zero = '0'
            report "Control reset output mismatch"
            severity error;

        reset <= '0';

        -- R-type (add).
        opcode <= "000000";
        wait for 10 ns;
        assert reg_dst = "01" and mem_to_reg = "00" and alu_op = "00" and
               jump = '0' and branch = '0' and mem_read = '0' and mem_write = '0' and
               alu_src = '0' and reg_write = '1' and sign_or_zero = '0'
            report "Control R-type output mismatch"
            severity error;

        -- slti.
        opcode <= "001010";
        wait for 10 ns;
        assert reg_dst = "00" and mem_to_reg = "00" and alu_op = "10" and
               jump = '0' and branch = '0' and mem_read = '0' and mem_write = '0' and
               alu_src = '1' and reg_write = '1' and sign_or_zero = '1'
            report "Control slti output mismatch"
            severity error;

        -- j.
        opcode <= "000010";
        wait for 10 ns;
        assert reg_dst = "00" and mem_to_reg = "00" and alu_op = "00" and
               jump = '1' and branch = '0' and mem_read = '0' and mem_write = '0' and
               alu_src = '0' and reg_write = '0' and sign_or_zero = '0'
            report "Control j output mismatch"
            severity error;

        -- jal.
        opcode <= "000011";
        wait for 10 ns;
        assert reg_dst = "10" and mem_to_reg = "10" and alu_op = "00" and
               jump = '1' and branch = '0' and mem_read = '0' and mem_write = '0' and
               alu_src = '0' and reg_write = '1' and sign_or_zero = '0'
            report "Control jal output mismatch"
            severity error;

        -- lw.
        opcode <= "100011";
        wait for 10 ns;
        assert reg_dst = "00" and mem_to_reg = "01" and alu_op = "11" and
               jump = '0' and branch = '0' and mem_read = '1' and mem_write = '0' and
               alu_src = '1' and reg_write = '1' and sign_or_zero = '1'
            report "Control lw output mismatch"
            severity error;

        -- sw.
        opcode <= "101011";
        wait for 10 ns;
        assert reg_dst = "00" and mem_to_reg = "00" and alu_op = "11" and
               jump = '0' and branch = '0' and mem_read = '0' and mem_write = '1' and
               alu_src = '1' and reg_write = '0' and sign_or_zero = '1'
            report "Control sw output mismatch"
            severity error;

        -- beq.
        opcode <= "000100";
        wait for 10 ns;
        assert reg_dst = "00" and mem_to_reg = "00" and alu_op = "01" and
               jump = '0' and branch = '1' and mem_read = '0' and mem_write = '0' and
               alu_src = '0' and reg_write = '0' and sign_or_zero = '1'
            report "Control beq output mismatch"
            severity error;

        -- addi.
        opcode <= "001000";
        wait for 10 ns;
        assert reg_dst = "00" and mem_to_reg = "00" and alu_op = "11" and
               jump = '0' and branch = '0' and mem_read = '0' and mem_write = '0' and
               alu_src = '1' and reg_write = '1' and sign_or_zero = '1'
            report "Control addi output mismatch"
            severity error;

        report "Simulation complete" severity note;
        wait;
    end process;
end Behavioral;

32bitCPU-VHDL/waves/TB_Control_Unit.vcd
$date
  Tue Mar 31 23:00:40 2026
$end
$version
  GHDL v0
$end
$timescale
  1 fs
$end
$scope module standard $end
$upscope $end
$scope module textio $end
$upscope $end
$scope module std_logic_1164 $end
$upscope $end
$scope module tb_control_unit $end
$var reg 6 ! opcode[5:0] $end
$var reg 1 " reset $end
$var reg 2 # reg_dst[1:0] $end
$var reg 2 $ mem_to_reg[1:0] $end
$var reg 2 % alu_op[1:0] $end
$var reg 1 & jump $end
$var reg 1 ' branch $end
$var reg 1 ( mem_read $end
$var reg 1 ) mem_write $end
$var reg 1 * alu_src $end
$var reg 1 + reg_write $end
$var reg 1 , sign_or_zero $end
$scope module uut $end
$var reg 6 - opcode[5:0] $end
$var reg 1 . reset $end
$var reg 2 / reg_dst[1:0] $end
$var reg 2 0 mem_to_reg[1:0] $end
$var reg 2 1 alu_op[1:0] $end
$var reg 1 2 jump $end
$var reg 1 3 branch $end
$var reg 1 4 mem_read $end
$var reg 1 5 mem_write $end
$var reg 1 6 alu_src $end
$var reg 1 7 reg_write $end
$var reg 1 8 sign_or_zero $end
$upscope $end
$upscope $end
$enddefinitions $end
#0
b000000 !
1"
b00 #
b00 $
b00 %
0&
0'
0(
0)
0*
0+
0,
b000000 -
1.
b00 /
b00 0
b00 1
02
03
04
05
06
07
08
#10000000
0"
b01 #
1+
0.
b01 /
17
#20000000
b001010 !
b00 #
b10 %
1*
1,
b001010 -
b00 /
b10 1
16
18
#30000000
b000010 !
b00 %
1&
0*
0+
0,
b000010 -
b00 1
12
06
07
08
#40000000
b000011 !
b10 #
b10 $
1+
b000011 -
b10 /
b10 0
17
#50000000
b100011 !
b00 #
b01 $
b11 %
0&
1(
1*
1,
b100011 -
b00 /
b01 0
b11 1
02
14
16
18
#60000000
b101011 !
b00 $
0(
1)
0+
b101011 -
b00 0
04
15
07
#70000000
b000100 !
b01 %
1'
0)
0*
b000100 -
b01 1
13
05
06
#80000000
b001000 !
b11 %
0'
1*
1+
b001000 -
b11 1
03
16
17
