32bitCPU-VHDL/src/Data_Memory.vhd
library IEEE;
use IEEE.STD_LOGIC_1164.ALL;
use IEEE.NUMERIC_STD.ALL;

-- File: Data_Memory.vhd
-- Entity: Data_Memory_VHDL
-- Description: 32-bit synchronous data memory with 256 words.
-- Author: <author>
-- Date: <date>

entity Data_Memory_VHDL is
    port (
        clk             : in  std_logic;
        mem_access_addr : in  std_logic_vector(31 downto 0);
        mem_write_data  : in  std_logic_vector(31 downto 0);
        mem_write_en    : in  std_logic;
        mem_read        : in  std_logic;
        mem_read_data   : out std_logic_vector(31 downto 0)
    );
end Data_Memory_VHDL;

architecture Behavioral of Data_Memory_VHDL is
    type ram_type is array (0 to 255) of std_logic_vector(31 downto 0);
    signal RAM : ram_type := (others => (others => '0'));
begin
    -- Synchronous read and write process.
    process (clk)
        variable addr_idx : integer range 0 to 255;
    begin
        if rising_edge(clk) then
            addr_idx := to_integer(unsigned(mem_access_addr(7 downto 0)));

            if mem_write_en = '1' then
                RAM(addr_idx) <= mem_write_data;
            end if;

            if mem_read = '1' then
                mem_read_data <= RAM(addr_idx);
            else
                mem_read_data <= x"00000000";
            end if;
        end if;
    end process;
end Behavioral;

32bitCPU-VHDL/testbench/TB_Data_Memory.vhd
library IEEE;
use IEEE.STD_LOGIC_1164.ALL;
use IEEE.NUMERIC_STD.ALL;

-- File: TB_Data_Memory.vhd
-- Entity: TB_Data_Memory
-- Description: Self-checking testbench for Data_Memory_VHDL.
-- Author: <author>
-- Date: <date>

entity TB_Data_Memory is
end TB_Data_Memory;

architecture Behavioral of TB_Data_Memory is
    signal clk             : std_logic := '0';
    signal mem_access_addr : std_logic_vector(31 downto 0) := (others => '0');
    signal mem_write_data  : std_logic_vector(31 downto 0) := (others => '0');
    signal mem_write_en    : std_logic := '0';
    signal mem_read        : std_logic := '0';
    signal mem_read_data   : std_logic_vector(31 downto 0);

    constant CLK_PERIOD : time := 10 ns;
begin
    uut: entity work.Data_Memory_VHDL
        port map (
            clk             => clk,
            mem_access_addr => mem_access_addr,
            mem_write_data  => mem_write_data,
            mem_write_en    => mem_write_en,
            mem_read        => mem_read,
            mem_read_data   => mem_read_data
        );

    clk_process: process
    begin
        while now < 300 ns loop
            clk <= '0';
            wait for CLK_PERIOD / 2;
            clk <= '1';
            wait for CLK_PERIOD / 2;
        end loop;
        wait;
    end process;

    stim_proc: process
    begin
        -- Test Case 1: Write/read address 2.
        mem_access_addr <= x"00000002";
        mem_write_data  <= x"00000400";
        mem_write_en    <= '1';
        mem_read        <= '0';
        wait for CLK_PERIOD;

        mem_write_en <= '0';
        mem_read     <= '1';
        wait for CLK_PERIOD;
        assert mem_read_data = x"00000400"
            report "Data Memory Test 1 failed: expected 0x00000400 at address 2"
            severity error;

        -- Test Case 2: Write/read address 4.
        mem_access_addr <= x"00000004";
        mem_write_data  <= x"00068EB8";
        mem_write_en    <= '1';
        mem_read        <= '0';
        wait for CLK_PERIOD;

        mem_write_en <= '0';
        mem_read     <= '1';
        wait for CLK_PERIOD;
        assert mem_read_data = x"00068EB8"
            report "Data Memory Test 2 failed: expected 0x00068EB8 at address 4"
            severity error;

        report "Simulation complete" severity note;
        wait;
    end process;
end Behavioral;

32bitCPU-VHDL/waves/TB_Data_Memory.vcd
$date
  Tue Mar 31 23:00:40 2026
$end
$version
  GHDL v0
$end
$timescale
  1 fs
$end
$scope module standard $end
$upscope $end
$scope module textio $end
$upscope $end
$scope module std_logic_1164 $end
$upscope $end
$scope module numeric_std $end
$upscope $end
$scope module tb_data_memory $end
$var reg 1 ! clk $end
$var reg 32 " mem_access_addr[31:0] $end
$var reg 32 # mem_write_data[31:0] $end
$var reg 1 $ mem_write_en $end
$var reg 1 % mem_read $end
$var reg 32 & mem_read_data[31:0] $end
$scope module uut $end
$var reg 1 ' clk $end
$var reg 32 ( mem_access_addr[31:0] $end
$var reg 32 ) mem_write_data[31:0] $end
$var reg 1 * mem_write_en $end
$var reg 1 + mem_read $end
$var reg 32 , mem_read_data[31:0] $end
$comment ram is not handled $end
$upscope $end
$upscope $end
$enddefinitions $end
#0
0!
b00000000000000000000000000000010 "
b00000000000000000000010000000000 #
1$
0%
bUUUUUUUUUUUUUUUUUUUUUUUUUUUUUUUU &
0'
b00000000000000000000000000000010 (
b00000000000000000000010000000000 )
1*
0+
bUUUUUUUUUUUUUUUUUUUUUUUUUUUUUUUU ,
#5000000
1!
b00000000000000000000000000000000 &
1'
b00000000000000000000000000000000 ,
#10000000
0!
0$
1%
0'
0*
1+
#15000000
1!
b00000000000000000000010000000000 &
1'
b00000000000000000000010000000000 ,
#20000000
0!
b00000000000000000000000000000100 "
b00000000000001101000111010111000 #
1$
0%
0'
b00000000000000000000000000000100 (
b00000000000001101000111010111000 )
1*
0+
#25000000
1!
b00000000000000000000000000000000 &
1'
b00000000000000000000000000000000 ,
#30000000
0!
0$
1%
0'
0*
1+
#35000000
1!
b00000000000001101000111010111000 &
1'
b00000000000001101000111010111000 ,
