32bitCPU-VHDL/src/Register_File.vhd
library IEEE;
use IEEE.STD_LOGIC_1164.ALL;
use IEEE.NUMERIC_STD.ALL;

-- File: Register_File.vhd
-- Entity: Register_File_VHDL
-- Description: 32x32 register file with sync write and comb read.
-- Author: <author>
-- Date: <date>

entity Register_File_VHDL is
    port (
        clk             : in  std_logic;
        rst             : in  std_logic;
        reg_write_en    : in  std_logic;
        reg_write_dest  : in  std_logic_vector(4 downto 0);
        reg_write_data  : in  std_logic_vector(31 downto 0);
        reg_read_addr_1 : in  std_logic_vector(4 downto 0);
        reg_read_addr_2 : in  std_logic_vector(4 downto 0);
        reg_read_data_1 : out std_logic_vector(31 downto 0);
        reg_read_data_2 : out std_logic_vector(31 downto 0)
    );
end Register_File_VHDL;

architecture Behavioral of Register_File_VHDL is
    type reg_array_type is array (0 to 31) of std_logic_vector(31 downto 0);
    signal registers : reg_array_type := (others => (others => '0'));
begin
    -- Synchronous reset and write process.
    process (clk, rst)
        variable write_idx : integer range 0 to 31;
    begin
        if rst = '1' then
            registers <= (others => x"00000000");
            registers(0) <= x"00000000";
            registers(1) <= x"00000001";
            registers(2) <= x"00000002";
            registers(3) <= x"00000003";
            registers(4) <= x"00000004";
            registers(5) <= x"00000005";
            registers(6) <= x"00000006";
            registers(7) <= x"00000007";
        elsif rising_edge(clk) then
            write_idx := to_integer(unsigned(reg_write_dest));
            if reg_write_en = '1' and write_idx /= 0 then
                registers(write_idx) <= reg_write_data;
            end if;
            registers(0) <= x"00000000";
        end if;
    end process;

    -- Combinational read port 1 with hardwired register 0 behavior.
    reg_read_data_1 <= x"00000000" when reg_read_addr_1 = "00000"
                       else registers(to_integer(unsigned(reg_read_addr_1)));

    -- Combinational read port 2 with hardwired register 0 behavior.
    reg_read_data_2 <= x"00000000" when reg_read_addr_2 = "00000"
                       else registers(to_integer(unsigned(reg_read_addr_2)));
end Behavioral;

32bitCPU-VHDL/testbench/TB_Register_File.vhd
library IEEE;
use IEEE.STD_LOGIC_1164.ALL;

-- File: TB_Register_File.vhd
-- Entity: TB_Register_File
-- Description: Self-checking testbench for Register_File_VHDL.
-- Author: <author>
-- Date: <date>

entity TB_Register_File is
end TB_Register_File;

architecture Behavioral of TB_Register_File is
    signal clk             : std_logic := '0';
    signal rst             : std_logic := '0';
    signal reg_write_en    : std_logic := '0';
    signal reg_write_dest  : std_logic_vector(4 downto 0) := (others => '0');
    signal reg_write_data  : std_logic_vector(31 downto 0) := (others => '0');
    signal reg_read_addr_1 : std_logic_vector(4 downto 0) := (others => '0');
    signal reg_read_addr_2 : std_logic_vector(4 downto 0) := (others => '0');
    signal reg_read_data_1 : std_logic_vector(31 downto 0);
    signal reg_read_data_2 : std_logic_vector(31 downto 0);

    constant CLK_PERIOD : time := 10 ns;
begin
    uut: entity work.Register_File_VHDL
        port map (
            clk             => clk,
            rst             => rst,
            reg_write_en    => reg_write_en,
            reg_write_dest  => reg_write_dest,
            reg_write_data  => reg_write_data,
            reg_read_addr_1 => reg_read_addr_1,
            reg_read_addr_2 => reg_read_addr_2,
            reg_read_data_1 => reg_read_data_1,
            reg_read_data_2 => reg_read_data_2
        );

    clk_process: process
    begin
        while now < 400 ns loop
            clk <= '0';
            wait for CLK_PERIOD / 2;
            clk <= '1';
            wait for CLK_PERIOD / 2;
        end loop;
        wait;
    end process;

    stim_proc: process
    begin
        -- Reset register file to known initial state.
        rst <= '1';
        wait for CLK_PERIOD;
        rst <= '0';

        -- Write register 1 = 0x001D8BCA.
        reg_write_en   <= '1';
        reg_write_dest <= "00001";
        reg_write_data <= x"001D8BCA";
        wait for CLK_PERIOD;

        -- Write register 3 = 0x0082B16F.
        reg_write_dest <= "00011";
        reg_write_data <= x"0082B16F";
        wait for CLK_PERIOD;

        -- Write register 5 = 0x0C25BB60.
        reg_write_dest <= "00101";
        reg_write_data <= x"0C25BB60";
        wait for CLK_PERIOD;

        -- Write register 7 = 0x013B23D4.
        reg_write_dest <= "00111";
        reg_write_data <= x"013B23D4";
        wait for CLK_PERIOD;

        reg_write_en <= '0';

        -- Read and verify register 1 and 3.
        reg_read_addr_1 <= "00001";
        reg_read_addr_2 <= "00011";
        wait for 5 ns;
        assert reg_read_data_1 = x"001D8BCA"
            report "Register 1 read failed"
            severity error;
        assert reg_read_data_2 = x"0082B16F"
            report "Register 3 read failed"
            severity error;

        -- Read and verify register 5 and 7.
        reg_read_addr_1 <= "00101";
        reg_read_addr_2 <= "00111";
        wait for 5 ns;
        assert reg_read_data_1 = x"0C25BB60"
            report "Register 5 read failed"
            severity error;
        assert reg_read_data_2 = x"013B23D4"
            report "Register 7 read failed"
            severity error;

        -- Register 0 must always read zero.
        reg_read_addr_1 <= "00000";
        wait for 5 ns;
        assert reg_read_data_1 = x"00000000"
            report "Register 0 is not hardwired to zero"
            severity error;

        report "Simulation complete" severity note;
        wait;
    end process;
end Behavioral;

32bitCPU-VHDL/waves/TB_Register_File.vcd
$date
  Tue Mar 31 23:00:40 2026
$end
$version
  GHDL v0
$end
$timescale
  1 fs
$end
$scope module standard $end
$upscope $end
$scope module textio $end
$upscope $end
$scope module std_logic_1164 $end
$upscope $end
$scope module numeric_std $end
$upscope $end
$scope module tb_register_file $end
$var reg 1 ! clk $end
$var reg 1 " rst $end
$var reg 1 # reg_write_en $end
$var reg 5 $ reg_write_dest[4:0] $end
$var reg 32 % reg_write_data[31:0] $end
$var reg 5 & reg_read_addr_1[4:0] $end
$var reg 5 ' reg_read_addr_2[4:0] $end
$var reg 32 ( reg_read_data_1[31:0] $end
$var reg 32 ) reg_read_data_2[31:0] $end
$scope module uut $end
$var reg 1 * clk $end
$var reg 1 + rst $end
$var reg 1 , reg_write_en $end
$var reg 5 - reg_write_dest[4:0] $end
$var reg 32 . reg_write_data[31:0] $end
$var reg 5 / reg_read_addr_1[4:0] $end
$var reg 5 0 reg_read_addr_2[4:0] $end
$var reg 32 1 reg_read_data_1[31:0] $end
$var reg 32 2 reg_read_data_2[31:0] $end
$comment registers is not handled $end
$upscope $end
$upscope $end
$enddefinitions $end
#0
0!
1"
0#
b00000 $
b00000000000000000000000000000000 %
b00000 &
b00000 '
b00000000000000000000000000000000 (
b00000000000000000000000000000000 )
0*
1+
0,
b00000 -
b00000000000000000000000000000000 .
b00000 /
b00000 0
b00000000000000000000000000000000 1
b00000000000000000000000000000000 2
#5000000
1!
1*
#10000000
0!
0"
1#
b00001 $
b00000000000111011000101111001010 %
0*
0+
1,
b00001 -
b00000000000111011000101111001010 .
#15000000
1!
1*
#20000000
0!
b00011 $
b00000000100000101011000101101111 %
0*
b00011 -
b00000000100000101011000101101111 .
#25000000
1!
1*
#30000000
0!
b00101 $
b00001100001001011011101101100000 %
0*
b00101 -
b00001100001001011011101101100000 .
#35000000
1!
1*
#40000000
0!
b00111 $
b00000001001110110010001111010100 %
0*
b00111 -
b00000001001110110010001111010100 .
#45000000
1!
1*
#50000000
0!
0#
b00001 &
b00011 '
b00000000000111011000101111001010 (
b00000000100000101011000101101111 )
0*
0,
b00001 /
b00011 0
b00000000000111011000101111001010 1
b00000000100000101011000101101111 2
#55000000
1!
b00101 &
b00111 '
b00001100001001011011101101100000 (
b00000001001110110010001111010100 )
1*
b00101 /
b00111 0
b00001100001001011011101101100000 1
b00000001001110110010001111010100 2
#60000000
0!
b00000 &
b00000000000000000000000000000000 (
0*
b00000 /
b00000000000000000000000000000000 1
